Metadata-Version: 2.1
Name: circuitpython-esp32connection
Version: 0.2.2
Summary: A WiFi connection helper for ESP32-based boards
Home-page: https://github.com/jimbobbennett/CircuitPython_ESP32Connection
Author: Jim Bennett
Author-email: jim.bennett@microsoft.com
License: MIT
Keywords: adafruit blinka circuitpython micropython esp32connection wifi esp32
Platform: UNKNOWN
Classifier: Development Status :: 3 - Alpha
Classifier: Intended Audience :: Developers
Classifier: Topic :: Software Development :: Libraries
Classifier: Topic :: System :: Hardware
Classifier: License :: OSI Approved :: MIT License
Classifier: Programming Language :: Python :: 3
Classifier: Programming Language :: Python :: 3.4
Classifier: Programming Language :: Python :: 3.5
